{
    "@odata.context": "/redfish/v1/$metadata#HpeServerPciDevice.HpeServerPciDevice",
    "@odata.etag": "W/\"D4AF705D\"",
    "@odata.id": "/redfish/v1/Systems/1/PCIDevices/18/",
    "@odata.type": "#HpeServerPciDevice.v2_0_0.HpeServerPciDevice",
    "Id": "18",
    "Bifurcated": "BifurcationNotSupported",
    "BusNumber": 201,
    "ClassCode": 3,
    "DeviceID": 8368,
    "DeviceInstance": 7,
    "DeviceLocation": "PCI-E Slot 7",
    "DeviceNumber": 0,
    "DeviceSubInstance": 2,
    "DeviceType": "Other PCI Device",
    "FunctionNumber": 0,
    "LocationString": "Slot 7",
    "Name": "NVIDIA A100-SXM4-40GB",
    "SegmentNumber": 0,
    "StructuredName": "PCI.Slot.7.2",
    "SubclassCode": 2,
    "SubsystemDeviceID": 4943,
    "SubsystemVendorID": 4318,
    "UEFIDevicePath": "PciRoot(0x5)/Pci(0x1,0x1)/Pci(0x0,0x0)/Pci(0x2,0x0)/Pci(0x0,0x0)/Pci(0x0,0x0)/Pci(0x0,0x0)",
    "VendorID": 4318
}