{
    "@odata.context": "/redfish/v1/$metadata#HpeServerPciDevice.HpeServerPciDevice",
    "@odata.etag": "W/\"9BEC373C\"",
    "@odata.id": "/redfish/v1/Systems/1/PCIDevices/6",
    "@odata.type": "#HpeServerPciDevice.v2_0_0.HpeServerPciDevice",
    "Id": "6",
    "BusNumber": 6,
    "ClassCode": 255,
    "DeviceID": 65535,
    "DeviceInstance": 12,
    "DeviceLocation": "Storage Controller Slot 12",
    "DeviceNumber": 0,
    "DeviceSubInstance": 1,
    "DeviceType": "Other PCI Device",
    "FunctionNumber": 0,
    "LocationString": "Storage Slot 12",
    "Name": "Empty Storage slot 12",
    "SegmentNumber": 0,
    "StructuredName": "PCI.Slot.12.1",
    "SubclassCode": 255,
    "SubsystemDeviceID": 65535,
    "SubsystemVendorID": 65535,
    "UEFIDevicePath": "PciRoot(0x3)/Pci(0x1,0x3)/Pci(0x0,0x0)",
    "VendorID": 65535
}