{
    "@odata.etag": "W/\"1649953581\"",
    "@odata.id": "/redfish/v1/Chassis/Node1/Sensors/ChassisVoltageRegulator0InputEnergy",
    "@odata.type": "#Sensor.v1_1_0.Sensor",
    "Id": "ChassisVoltageRegulator0InputEnergy",
    "Name": "Node",
    "Oem": {
        "Index": 0,
        "ParentalContext": "Chassis"
    },
    "PhysicalContext": "VoltageRegulator",
    "PhysicalSubContext": "Input",
    "Reading": 455517408,
    "ReadingTime": "2022-04-14T16:26:44.444065344Z",
    "ReadingType": "EnergyJoules",
    "ReadingUnits": "J"
}