{
    "@odata.context": "/redfish/v1/$metadata#HpeServerPCISlot.HpeServerPCISlot",
    "@odata.etag": "W/\"2F5D0903\"",
    "@odata.id": "/redfish/v1/Systems/1/PCISlots/11/",
    "@odata.type": "#HpeServerPCISlot.v2_1_1.HpeServerPCISlot",
    "Id": "11",
    "BusNumber": 69,
    "Characteristics": {
        "Provides3_3Volts": true,
        "SupportsPowerManagementEventSignal": true
    },
    "DeviceNumber": 0,
    "FunctionNumber": 0,
    "Length": "Long",
    "LinkLanes": "x16",
    "Name": "PCI-E Slot 18",
    "Status": {
        "OperationalStatus": [
            {
                "Status": "InUse"
            }
        ]
    },
    "SupportsHotPlug": false,
    "Technology": "PCIExpressGen4",
    "UEFIDevicePath": "PciRoot(0x1)/Pci(0x1,0x1)/Pci(0x0,0x0)/Pci(0x0,0x0)/Pci(0x0,0x0)"
}